WatchMySASS/WatchMySASS.py
WatchMySASS/__init__.py
WatchMySASS/observer.py
WatchMySASS/utils.py
WatchMySASS-0.1.5.dist-info/METADATA
WatchMySASS-0.1.5.dist-info/WHEEL
WatchMySASS-0.1.5.dist-info/entry_points.txt
WatchMySASS-0.1.5.dist-info/top_level.txt
WatchMySASS-0.1.5.dist-info/RECORD
