Metadata-Version: 2.1
Name: WatchMySASS
Version: 0.1.5
Summary: Compile SCSS inside of HTML files.
Home-page: https://github.com/DevonWieczorek/WatchMySASS
Author: Devon Wieczorek
Author-email: devon.wieczorek93@gmail.com
License: MIT
Keywords: SCSS compiler html/scss
Platform: UNKNOWN
Classifier: Development Status :: 4 - Beta
Classifier: Environment :: Console
Classifier: Intended Audience :: Developers
Classifier: License :: OSI Approved :: MIT License
Classifier: Natural Language :: English
Classifier: Operating System :: OS Independent
Classifier: Programming Language :: Python :: 2.7
Classifier: Topic :: Software Development :: Compilers
Requires-Dist: pyScss
Requires-Dist: beautifulsoup4
Requires-Dist: argparse
Requires-Dist: watchdog
